MANIFEST.in
README.rst
setup.py
occiput/__init__.py
occiput/global_settings.py
occiput/version.py
occiput.egg-info/PKG-INFO
occiput.egg-info/SOURCES.txt
occiput.egg-info/dependency_links.txt
occiput.egg-info/requires.txt
occiput.egg-info/top_level.txt
occiput/Classification/__init__.py
occiput/Core/Conversion.py
occiput/Core/Core.py
occiput/Core/Errors.py
occiput/Core/NiftyPy_wrap.py
occiput/Core/Print.py
occiput/Core/__init__.py
occiput/Core/transformations.py
occiput/Data/occiput_ray_tracer_PET.pdf
occiput/Data/occiput_ray_tracer_PET.png
occiput/Data/occiput_ray_tracer_PET.svg
occiput/DataSources/__init__.py
occiput/DataSources/FileSources/Files.py
occiput/DataSources/FileSources/LookupTable.py
occiput/DataSources/FileSources/MR_kspace.py
occiput/DataSources/FileSources/MR_motion_sensors.py
occiput/DataSources/FileSources/PET_listmode.py
occiput/DataSources/FileSources/PET_projection.py
occiput/DataSources/FileSources/PET_volume.py
occiput/DataSources/FileSources/Physiology.py
occiput/DataSources/FileSources/Volume.py
occiput/DataSources/FileSources/Web.py
occiput/DataSources/FileSources/__init__.py
occiput/DataSources/FileSources/vNAV.py
occiput/DataSources/Synthetic/Shapes.py
occiput/DataSources/Synthetic/__init__.py
occiput/Reconstruction/__init__.py
occiput/Reconstruction/CT/__init__.py
occiput/Reconstruction/MR/MR.py
occiput/Reconstruction/MR/MR_ilang.py
occiput/Reconstruction/MR/__init__.py
occiput/Reconstruction/PET/PET.py
occiput/Reconstruction/PET/PET_ilang.py
occiput/Reconstruction/PET/PET_listmode.py
occiput/Reconstruction/PET/PET_meshing.py
occiput/Reconstruction/PET/PET_projection.py
occiput/Reconstruction/PET/PET_raytracer.py
occiput/Reconstruction/PET/PET_scanners.py
occiput/Reconstruction/PET/PET_span.py
occiput/Reconstruction/PET/PET_subsets.py
occiput/Reconstruction/PET/__init__.py
occiput/Reconstruction/SPECT/Collimators.py
occiput/Reconstruction/SPECT/SPECT.py
occiput/Reconstruction/SPECT/Scintillators.py
occiput/Reconstruction/SPECT/__init__.py
occiput/Registration/__init__.py
occiput/Registration/Affine/__init__.py
occiput/Registration/TranslationRotation/__init__.py
