Metadata-Version: 1.1
Name: occiput
Version: 1.0.9
Summary: Tomographic Vision - PET, SPECT, CT, MRI reconstruction and processing.
Home-page: http://www.occiput.io/
Author: Stefano Pedemonte
Author-email: stefano.pedemonte@gmail.com
License: LICENSE.txt
Keywords: PET,SPECT,emission tomography,transmission tomography,tomographic reconstruction,nuclear magnetic resonance
Platform: UNKNOWN
Classifier: Programming Language :: Python
Classifier: Development Status :: 4 - Beta
Classifier: Environment :: Other Environment
Classifier: Intended Audience :: Science/Research
Classifier: License :: OSI Approved :: BSD License
Classifier: Operating System :: OS Independent
Classifier: Topic :: Scientific/Engineering :: Medical Science Apps.
Classifier: Topic :: Scientific/Engineering :: Mathematics
Classifier: Topic :: Scientific/Engineering :: Bio-Informatics
